{
  "team_id": "CITY_FC",
  "team_name": "City FC",
  "manager_id": "mourinho",
  "formation": "4-4-2",
  "roster": [
    {
      "player_id": "CITY_GK_1",
      "player_name": "David Stone",
      "age": 28,
      "primary_position": "GK",
      "current_position": "GK",
      "familiar_positions": [],
      "speed": 8,
      "acceleration": 8,
      "strength": 12,
      "stamina": 14,
      "vision": 10,
      "intelligence": 12,
      "marking": 6,
      "positioning": 14,
      "dribbling": 6,
      "ball_control": 10,
      "short_pass": 10,
      "long_pass": 12,
      "crossing": 6,
      "shot_power": 8,
      "shot_accuracy": 6,
      "tackling": 8,
      "heading": 12,
      "reflexes": 16,
      "diving": 16,
      "handling": 15,
      "potential_cap": 250,
      "current_stamina_percent": 100.0,
      "morale": 80,
      "match_fitness": 100.0
    },
    {
      "player_id": "CITY_LB_1",
      "player_name": "Marcus Shaw",
      "age": 25,
      "primary_position": "LB",
      "current_position": "LB",
      "familiar_positions": ["LWB", "LM"],
      "speed": 14,
      "acceleration": 13,
      "strength": 11,
      "stamina": 13,
      "vision": 11,
      "intelligence": 11,
      "marking": 13,
      "positioning": 12,
      "dribbling": 10,
      "ball_control": 11,
      "short_pass": 11,
      "long_pass": 10,
      "crossing": 12,
      "shot_power": 8,
      "shot_accuracy": 7,
      "tackling": 13,
      "heading": 10,
      "reflexes": 8,
      "diving": 6,
      "handling": 6,
      "potential_cap": 250,
      "current_stamina_percent": 100.0,
      "morale": 75,
      "match_fitness": 100.0
    },
    {
      "player_id": "CITY_CB1_1",
      "player_name": "Leo Ramos",
      "age": 27,
      "primary_position": "CB1",
      "current_position": "CB1",
      "familiar_positions": ["CB2"],
      "speed": 10,
      "acceleration": 10,
      "strength": 15,
      "stamina": 12,
      "vision": 10,
      "intelligence": 13,
      "marking": 14,
      "positioning": 14,
      "dribbling": 7,
      "ball_control": 8,
      "short_pass": 10,
      "long_pass": 10,
      "crossing": 6,
      "shot_power": 9,
      "shot_accuracy": 7,
      "tackling": 15,
      "heading": 14,
      "reflexes": 8,
      "diving": 6,
      "handling": 6,
      "potential_cap": 250,
      "current_stamina_percent": 100.0,
      "morale": 80,
      "match_fitness": 100.0
    },
    {
      "player_id": "CITY_CB2_1",
      "player_name": "Ivan Petrov",
      "age": 29,
      "primary_position": "CB2",
      "current_position": "CB2",
      "familiar_positions": ["CB1"],
      "speed": 9,
      "acceleration": 9,
      "strength": 16,
      "stamina": 12,
      "vision": 11,
      "intelligence": 14,
      "marking": 15,
      "positioning": 15,
      "dribbling": 6,
      "ball_control": 7,
      "short_pass": 9,
      "long_pass": 11,
      "crossing": 5,
      "shot_power": 10,
      "shot_accuracy": 6,
      "tackling": 16,
      "heading": 15,
      "reflexes": 7,
      "diving": 5,
      "handling": 5,
      "potential_cap": 250,
      "current_stamina_percent": 100.0,
      "morale": 85,
      "match_fitness": 100.0
    },
    {
      "player_id": "CITY_RB_1",
      "player_name": "James Walker",
      "age": 24,
      "primary_position": "RB",
      "current_position": "RB",
      "familiar_positions": ["RWB", "RM"],
      "speed": 15,
      "acceleration": 14,
      "strength": 10,
      "stamina": 14,
      "vision": 12,
      "intelligence": 11,
      "marking": 12,
      "positioning": 11,
      "dribbling": 11,
      "ball_control": 12,
      "short_pass": 12,
      "long_pass": 11,
      "crossing": 13,
      "shot_power": 9,
      "shot_accuracy": 8,
      "tackling": 12,
      "heading": 9,
      "reflexes": 9,
      "diving": 6,
      "handling": 6,
      "potential_cap": 250,
      "current_stamina_percent": 100.0,
      "morale": 78,
      "match_fitness": 100.0
    },
    {
      "player_id": "CITY_LM_1",
      "player_name": "Andre Silva",
      "age": 23,
      "primary_position": "LM",
      "current_position": "LM",
      "familiar_positions": ["LW", "LB"],
      "speed": 14,
      "acceleration": 15,
      "strength": 9,
      "stamina": 13,
      "vision": 13,
      "intelligence": 12,
      "marking": 9,
      "positioning": 11,
      "dribbling": 14,
      "ball_control": 14,
      "short_pass": 13,
      "long_pass": 11,
      "crossing": 14,
      "shot_power": 11,
      "shot_accuracy": 10,
      "tackling": 9,
      "heading": 8,
      "reflexes": 8,
      "diving": 6,
      "handling": 6,
      "potential_cap": 250,
      "current_stamina_percent": 100.0,
      "morale": 82,
      "match_fitness": 100.0
    },
    {
      "player_id": "CITY_CM1_1",
      "player_name": "Liam Murphy",
      "age": 26,
      "primary_position": "CM1",
      "current_position": "CM1",
      "familiar_positions": ["CM2", "CDM"],
      "speed": 11,
      "acceleration": 11,
      "strength": 12,
      "stamina": 14,
      "vision": 14,
      "intelligence": 14,
      "marking": 11,
      "positioning": 13,
      "dribbling": 12,
      "ball_control": 13,
      "short_pass": 14,
      "long_pass": 13,
      "crossing": 10,
      "shot_power": 12,
      "shot_accuracy": 11,
      "tackling": 11,
      "heading": 10,
      "reflexes": 8,
      "diving": 6,
      "handling": 6,
      "potential_cap": 250,
      "current_stamina_percent": 100.0,
      "morale": 80,
      "match_fitness": 100.0
    },
    {
      "player_id": "CITY_CM2_1",
      "player_name": "Pablo Martinez",
      "age": 25,
      "primary_position": "CM2",
      "current_position": "CM2",
      "familiar_positions": ["CM1", "CAM"],
      "speed": 12,
      "acceleration": 12,
      "strength": 10,
      "stamina": 13,
      "vision": 15,
      "intelligence": 15,
      "marking": 10,
      "positioning": 12,
      "dribbling": 13,
      "ball_control": 14,
      "short_pass": 15,
      "long_pass": 14,
      "crossing": 11,
      "shot_power": 13,
      "shot_accuracy": 12,
      "tackling": 10,
      "heading": 9,
      "reflexes": 8,
      "diving": 6,
      "handling": 6,
      "potential_cap": 250,
      "current_stamina_percent": 100.0,
      "morale": 85,
      "match_fitness": 100.0
    },
    {
      "player_id": "CITY_RM_1",
      "player_name": "Tom Richards",
      "age": 22,
      "primary_position": "RM",
      "current_position": "RM",
      "familiar_positions": ["RW", "RB"],
      "speed": 16,
      "acceleration": 16,
      "strength": 8,
      "stamina": 12,
      "vision": 12,
      "intelligence": 11,
      "marking": 8,
      "positioning": 10,
      "dribbling": 15,
      "ball_control": 15,
      "short_pass": 12,
      "long_pass": 10,
      "crossing": 15,
      "shot_power": 12,
      "shot_accuracy": 11,
      "tackling": 8,
      "heading": 7,
      "reflexes": 9,
      "diving": 6,
      "handling": 6,
      "potential_cap": 250,
      "current_stamina_percent": 100.0,
      "morale": 80,
      "match_fitness": 100.0
    },
    {
      "player_id": "CITY_ST1_1",
      "player_name": "Carlos Hernandez",
      "age": 28,
      "primary_position": "ST1",
      "current_position": "ST1",
      "familiar_positions": ["ST2", "CF"],
      "speed": 14,
      "acceleration": 14,
      "strength": 13,
      "stamina": 12,
      "vision": 13,
      "intelligence": 13,
      "marking": 7,
      "positioning": 15,
      "dribbling": 14,
      "ball_control": 14,
      "short_pass": 12,
      "long_pass": 9,
      "crossing": 9,
      "shot_power": 16,
      "shot_accuracy": 15,
      "tackling": 7,
      "heading": 13,
      "reflexes": 8,
      "diving": 6,
      "handling": 6,
      "potential_cap": 250,
      "current_stamina_percent": 100.0,
      "morale": 88,
      "match_fitness": 100.0
    },
    {
      "player_id": "CITY_ST2_1",
      "player_name": "Jake Anderson",
      "age": 26,
      "primary_position": "ST2",
      "current_position": "ST2",
      "familiar_positions": ["ST1", "CF"],
      "speed": 15,
      "acceleration": 15,
      "strength": 12,
      "stamina": 13,
      "vision": 12,
      "intelligence": 12,
      "marking": 6,
      "positioning": 14,
      "dribbling": 15,
      "ball_control": 15,
      "short_pass": 11,
      "long_pass": 8,
      "crossing": 8,
      "shot_power": 15,
      "shot_accuracy": 14,
      "tackling": 6,
      "heading": 12,
      "reflexes": 8,
      "diving": 6,
      "handling": 6,
      "potential_cap": 250,
      "current_stamina_percent": 100.0,
      "morale": 85,
      "match_fitness": 100.0
    }
  ]
}
